ensembl/core/__init__.py
ensembl/core/models.py
ensembl/ncbi_taxonomy/__init__.py
ensembl/ncbi_taxonomy/models.py
ensembl/ncbi_taxonomy/api/__init__.py
ensembl/ncbi_taxonomy/api/utils.py
ensembl/xrefs/xref_source_db_model.py
ensembl/xrefs/xref_update_db_model.py
ensembl_py-3.0.1.dist-info/licenses/LICENSE
ensembl_py-3.0.1.dist-info/licenses/NOTICE
ensembl_py-3.0.1.dist-info/METADATA
ensembl_py-3.0.1.dist-info/WHEEL
ensembl_py-3.0.1.dist-info/top_level.txt
ensembl_py-3.0.1.dist-info/RECORD
