Metadata-Version: 2.4
Name: ensembl-py
Version: 3.0.1
Summary: Ensembl Python Base Library
Author-email: Ensembl <dev@ensembl.org>
License-Expression: Apache-2.0
Project-URL: Homepage, https://www.ensembl.org
Project-URL: Documentation, https://ensembl.github.io/ensembl-py/
Project-URL: Repository, https://github.com/Ensembl/ensembl-py.git
Project-URL: Issues, https://github.com/Ensembl/ensembl-py/issues
Keywords: ensembl,bioinformatics,python,setup
Classifier: Development Status :: 4 - Beta
Classifier: Environment :: Console
Classifier: Intended Audience :: Science/Research
Classifier: Operating System :: OS Independent
Classifier: Programming Language :: Python
Classifier: Programming Language :: Python :: 3
Classifier: Programming Language :: Python :: 3 :: Only
Classifier: Programming Language :: Python :: 3.10
Classifier: Programming Language :: Python :: 3.11
Classifier: Topic :: Scientific/Engineering :: Bio-Informatics
Classifier: Topic :: Software Development :: Libraries :: Python Modules
Requires-Python: >=3.10
License-File: LICENSE
License-File: NOTICE
Requires-Dist: sqlalchemy>=1.4.45
Provides-Extra: build
Requires-Dist: build; extra == "build"
Requires-Dist: setuptools; extra == "build"
Requires-Dist: setuptools-scm; extra == "build"
Requires-Dist: wheel; extra == "build"
Provides-Extra: cicd
Requires-Dist: black; extra == "cicd"
Requires-Dist: coverage; extra == "cicd"
Requires-Dist: ensembl-utils>=0.5.0; extra == "cicd"
Requires-Dist: genbadge[coverage]; extra == "cicd"
Requires-Dist: mypy; extra == "cicd"
Requires-Dist: pylint; extra == "cicd"
Requires-Dist: pytest; extra == "cicd"
Requires-Dist: pytest-dependency; extra == "cicd"
Requires-Dist: pytest-mock; extra == "cicd"
Requires-Dist: requests-mock>=1.8.0; extra == "cicd"
Requires-Dist: types-PyYAML; extra == "cicd"
Requires-Dist: types-requests; extra == "cicd"
Provides-Extra: dev
Requires-Dist: ipython; extra == "dev"
Provides-Extra: docs
Requires-Dist: mkdocs>=1.5.3; extra == "docs"
Requires-Dist: mkdocs-autorefs; extra == "docs"
Requires-Dist: mkdocs-coverage; extra == "docs"
Requires-Dist: mkdocs-gen-files; extra == "docs"
Requires-Dist: mkdocs-literate-nav; extra == "docs"
Requires-Dist: mkdocs-material; extra == "docs"
Requires-Dist: mkdocs-material-extensions; extra == "docs"
Requires-Dist: mkdocs-section-index; extra == "docs"
Requires-Dist: mkdocstrings; extra == "docs"
Requires-Dist: mkdocstrings-python; extra == "docs"
Provides-Extra: mysql
Requires-Dist: mysqlclient<2.3.0,>=1.4.6; extra == "mysql"
Dynamic: license-file
